indipydriver/__init__.py
indipydriver/events.py
indipydriver/ipydriver.py
indipydriver/propertymembers.py
indipydriver/propertyvectors.py
indipydriver-3.0.4.dist-info/licenses/LICENSE
indipydriver-3.0.4.dist-info/WHEEL
indipydriver-3.0.4.dist-info/METADATA
indipydriver-3.0.4.dist-info/RECORD
