Metadata-Version: 2.4
Name: indipydriver
Version: 3.0.4
Summary: Enable drivers to be written for instrument control using the INDI protocol.
Keywords: indi,driver,astronomy,instrument,remote,control
Author-email: Bernard Czenkusz <bernie@skipole.co.uk>
Requires-Python: >=3.11
Classifier: License :: OSI Approved :: MIT License
Classifier: Operating System :: POSIX :: Linux
Classifier: Topic :: Scientific/Engineering :: Astronomy
Classifier: Topic :: Scientific/Engineering :: Interface Engine/Protocol Translator
License-File: LICENSE
Project-URL: Documentation, https://indipydriver.readthedocs.io
Project-URL: Source, https://github.com/bernie-skipole/indipydriver
